viscat/data_preparation.py
viscat/neo.py
viscat-0.0.2.dist-info/METADATA
viscat-0.0.2.dist-info/WHEEL
viscat-0.0.2.dist-info/top_level.txt
viscat-0.0.2.dist-info/RECORD
