Metadata-Version: 2.1
Name: viscat
Version: 0.0.2
Summary: Visualization of a dataset annotated with CAT
Home-page: https://github.com/w-is-h/viscat
Author: w-is-h
Author-email: w.kraljevic@gmail.com
License: UNKNOWN
Platform: UNKNOWN
Classifier: Programming Language :: Python :: 3
Classifier: License :: OSI Approved :: MIT License
Classifier: Operating System :: OS Independent
Requires-Dist: py2neo (==2021.2.3)
Requires-Dist: pandas (==1.3.4)
